{"type":"PR","pr":{"number":43,"head":"887d3f34f71a95d06508678b381f4fe3fd26fab6"},"user":"tom.janssens","status":"pending_publish","branch":"cms/notification","collection":"notifications","title":" Lessen afgelast wegens COVID-19 Virus","description":"Conform met de beslissingen van de Nationale Veiligheidsraad zijn de lessen voor onbepaalde duur afgelast. We hopen jou snel terug van dienst te zijn! ","objects":{"entry":{"path":"src/markdown/notification.md","sha":"40fb9aa5d05c2cae3baaa5b4817fbf4405877a2a"},"files":[]},"timeStamp":"2020-03-14T15:42:10.613Z"}